pycedar.cpython-35m-i386-linux-gnu.so
pycedar/VERSION
pycedar/pycedar.pxd
pycedar/core/cedar/src/cedarpp.h
pycedar-0.1.3.dist-info/METADATA
pycedar-0.1.3.dist-info/RECORD
pycedar-0.1.3.dist-info/WHEEL
pycedar-0.1.3.dist-info/top_level.txt
