Metadata-Version: 2.1
Name: pycedar
Version: 0.1.3
Summary: Python binding of cedar (implementation of efficiently-updatable double-array trie) using Cython
Home-page: https://github.com/akivajp/pycedar
Author: Akiva Miura
Author-email: akiva.miura@gmail.com
License: GPLv2, GPLv2.1 and BSD
Platform: UNKNOWN
Classifier: Programming Language :: Python
Classifier: Programming Language :: Python :: 3.5
Classifier: Programming Language :: Python :: 3.6
Classifier: Programming Language :: Python :: 3.7
Classifier: Topic :: Utilities
